README.md
setup.py
dicaso/__init__.py
dicaso.egg-info/PKG-INFO
dicaso.egg-info/SOURCES.txt
dicaso.egg-info/dependency_links.txt
dicaso.egg-info/entry_points.txt
dicaso.egg-info/not-zip-safe
dicaso.egg-info/requires.txt
dicaso.egg-info/top_level.txt