Metadata-Version: 2.1
Name: dicaso
Version: 0.0.1
Summary: Digital Caviar Solutions software suite
Home-page: https://github.com/dicaso/dicaso
Author: Christophe Van Neste
Author-email: christophe.vanneste@ugent.be
License: MIT
Platform: UNKNOWN
Requires-Python: >3.6
Provides-Extra: development
